tubex/__init__.py
tubex/cli.py
tubex/mp3.py
tubex/mp4.py
tubex/utils.py
tubex-0.3.0.dist-info/LICENSE
tubex-0.3.0.dist-info/METADATA
tubex-0.3.0.dist-info/WHEEL
tubex-0.3.0.dist-info/entry_points.txt
tubex-0.3.0.dist-info/top_level.txt
tubex-0.3.0.dist-info/RECORD
