Metadata-Version: 2.1
Name: tubex
Version: 0.3.0
Summary: Command Line Interface to download MP3 from youtube and MP4 from oreilly
Home-page: https://github.com/ricky-lim/tubex
Author: Ricky Lim
Author-email: rlim.email@gmail.com
License: UNKNOWN
Platform: UNKNOWN
Classifier: Programming Language :: Python :: 3
Classifier: License :: OSI Approved :: MIT License
Classifier: Operating System :: OS Independent
Requires-Python: >=3.7
Requires-Dist: youtube-dl (==2021.1.8)
Requires-Dist: eyeD3 (==0.9.6)
Requires-Dist: Click (==7.1.2)
Requires-Dist: ffmpeg-python (==0.2.0)
Requires-Dist: tqdm (==4.55.2)
